pystack3d/__init__.py
pystack3d/bkg_removal.py
pystack3d/cropping.py
pystack3d/destriping.py
pystack3d/intensity_rescaling.py
pystack3d/intensity_rescaling_area.py
pystack3d/registration_calculation.py
pystack3d/registration_transformation.py
pystack3d/resampling.py
pystack3d/stack3d.py
pystack3d/utils.py
pystack3d/utils_metadata_fibics.py
pystack3d/utils_multiprocessing.py
pystack3d/assets/params.toml
pystack3d-2025.3.dist-info/licenses/LICENSE
pystack3d-2025.3.dist-info/METADATA
pystack3d-2025.3.dist-info/WHEEL
pystack3d-2025.3.dist-info/top_level.txt
pystack3d-2025.3.dist-info/RECORD
