Metadata-Version: 2.4
Name: pystack3d
Version: 2025.3
Summary: Pystack3D: A Python package for fast image stack correction
Author-email: Patrick Quéméré <patrick.quemere@cea.fr>
License: GPL v3
Project-URL: Homepage, https://github.dev/CEA-MetroCarac/pystack3d
Project-URL: Documentation, https://cea-metrocarac.github.io/pystack3d/index.html
Keywords: PyStack3D,stack,images,FIB-SEM,processing,correction,cropping,background removal,registration,intensity rescaling,destriping,curtains,resampling,multithreading,multiprocessing
Classifier: Programming Language :: Python :: 3
Classifier: Programming Language :: Python :: 3.8
Classifier: Programming Language :: Python :: 3.9
Classifier: Programming Language :: Python :: 3.10
Classifier: Programming Language :: Python :: 3.11
Classifier: Programming Language :: Python :: 3.12
Classifier: License :: OSI Approved :: GNU General Public License v3 (GPLv3)
Classifier: Operating System :: Microsoft :: Windows
Classifier: Operating System :: POSIX :: Linux
Classifier: Operating System :: MacOS :: MacOS X
Classifier: Environment :: Console
Requires-Python: >=3.8
License-File: LICENSE
Requires-Dist: numpy
Requires-Dist: matplotlib
Requires-Dist: scipy
Requires-Dist: scikit-image
Requires-Dist: statsmodels
Requires-Dist: pystackreg
Requires-Dist: pyvsnr
Requires-Dist: PyWavelets
Requires-Dist: Pillow
Requires-Dist: tifffile
Requires-Dist: tomli
Requires-Dist: tomlkit
Requires-Dist: parse
Requires-Dist: lxml
Provides-Extra: gui
Requires-Dist: pystack3d-napari; extra == "gui"
Dynamic: license-file
